{
  "missions": [
    {
      "id": "SubYoutube1",
      "name": "Youtube",
      "author": "Kadoy",
      "conditions": "forever / 3$",
      "difficulty": 3,
      "difficultyDescription": "Are you crazy?",
      "experience": "+ 0.0001%",
      "duration": 15
    },
    {
      "id": "SubYoutube2",
      "name": "Youtube",
      "author": "Kadoy",
      "conditions": "forever / 3$",
      "difficulty": 3,
      "difficultyDescription": "Are you crazy?",
      "experience": "+ 0.0001%",
      "duration": 15
    },
    {
      "id": "SubYoutube3",
      "name": "Youtube",
      "author": "Kadoy",
      "conditions": "forever / 3$",
      "difficulty": 3,
      "difficultyDescription": "Are you crazy?",
      "experience": "+ 0.0001%",
      "duration": 15
    },
    {
      "id": "SubYoutube4",
      "name": "Youtube",
      "author": "Kadoy",
      "conditions": "forever / 3$",
      "difficulty": 3,
      "difficultyDescription": "Are you crazy?",
      "experience": "+ 0.0001%",
      "duration": 15
    },
    {
      "id": "SubYoutube5",
      "name": "Youtube",
      "author": "Kadoy",
      "conditions": "forever / 3$",
      "difficulty": 3,
      "difficultyDescription": "Are you crazy?",
      "experience": "+ 0.0001%",
      "duration": 15
    },
    {
      "id": "SubYoutube6",
      "name": "Youtube",
      "author": "Kadoy",
      "conditions": "forever / 3$",
      "difficulty": 3,
      "difficultyDescription": "Are you crazy?",
      "experience": "+ 0.0001%",
      "duration": 15
    },
    {
      "id": "SubYoutube7",
      "name": "Youtube",
      "author": "Kadoy",
      "conditions": "forever / 3$",
      "difficulty": 3,
      "difficultyDescription": "Are you crazy?",
      "experience": "+ 0.0001%",
      "duration": 15
    },
    {
      "id": "EgorYoutube15",
      "name": "Youtube",
      "author": "Kadoy",
      "conditions": "forever / 3$",
      "difficulty": 3,
      "difficultyDescription": "Are you crazy?",
      "experience": "+ 0.0001%",
      "duration": 15
    },
    {
      "id": "EgorYoutube15",
      "name": "Youtube",
      "author": "Kadoy",
      "conditions": "forever / 3$",
      "difficulty": 3,
      "difficultyDescription": "Are you crazy?",
      "experience": "+ 0.0001%",
      "duration": 15
    },
    {
      "id": "EgorYoutube15",
      "name": "Youtube",
      "author": "Kadoy",
      "conditions": "forever / 3$",
      "difficulty": 3,
      "difficultyDescription": "Are you crazy?",
      "experience": "+ 0.0001%",
      "duration": 15
    },
    {
      "id": "EgorYoutube15",
      "name": "Youtube",
      "author": "Kadoy",
      "conditions": "forever / 3$",
      "difficulty": 3,
      "difficultyDescription": "Are you crazy?",
      "experience": "+ 0.0001%",
      "duration": 15
    }
  ]
}